<?xml version="1.0" encoding="utf-8" ?><dwsync><file name=".DS_Store" server="s34242.gridserver.com//domains/nickbarfuss.com/html/battlegame/" local="3564798667" remote="3565917840" Dst="-1" /><file name=".DS_Store" server="Macintosh HD/Applications/MAMP/htdocs/battlegame/" local="3564798667" remote="3564798667" Dst="-1" /><file name="_animated.scss" server="Macintosh HD/Applications/MAMP/htdocs/battlegame/" local="3563553260" remote="3563553260" Dst="-1" /><file name="_bordered-pulled.scss" server="Macintosh HD/Applications/MAMP/htdocs/battlegame/" local="3563553260" remote="3563553260" Dst="-1" /><file name="_core.scss" server="Macintosh HD/Applications/MAMP/htdocs/battlegame/" local="3563553260" remote="3563553260" Dst="-1" /><file name="_fixed-width.scss" server="Macintosh HD/Applications/MAMP/htdocs/battlegame/" local="3563553260" remote="3563553260" Dst="-1" /><file name="_icons.scss" server="Macintosh HD/Applications/MAMP/htdocs/battlegame/" local="3563553260" remote="3563553260" Dst="-1" /><file name="_larger.scss" server="Macintosh HD/Applications/MAMP/htdocs/battlegame/" local="3563553260" remote="3563553260" Dst="-1" /><file name="_list.scss" server="Macintosh HD/Applications/MAMP/htdocs/battlegame/" local="3563553260" remote="3563553260" Dst="-1" /><file name="_mixins.scss" server="Macintosh HD/Applications/MAMP/htdocs/battlegame/" local="3563553260" remote="3563553260" Dst="-1" /><file name="_path.scss" server="Macintosh HD/Applications/MAMP/htdocs/battlegame/" local="3563553260" remote="3563553260" Dst="-1" /><file name="_rotated-flipped.scss" server="Macintosh HD/Applications/MAMP/htdocs/battlegame/" local="3563553260" remote="3563553260" Dst="-1" /><file name="_screen-reader.scss" server="Macintosh HD/Applications/MAMP/htdocs/battlegame/" local="3563553260" remote="3563553260" Dst="-1" /><file name="_stacked.scss" server="Macintosh HD/Applications/MAMP/htdocs/battlegame/" local="3563553260" remote="3563553260" Dst="-1" /><file name="_variables.scss" server="Macintosh HD/Applications/MAMP/htdocs/battlegame/" local="3564496068" remote="3564496068" Dst="-1" /><file name="_animated.scss" server="s34242.gridserver.com//domains/nickbarfuss.com/html/battlegame/" local="3563553260" remote="3565917840" Dst="-1" /><file name="_bordered-pulled.scss" server="s34242.gridserver.com//domains/nickbarfuss.com/html/battlegame/" local="3563553260" remote="3565917840" Dst="-1" /><file name="_core.scss" server="s34242.gridserver.com//domains/nickbarfuss.com/html/battlegame/" local="3563553260" remote="3565917840" Dst="-1" /><file name="_fixed-width.scss" server="s34242.gridserver.com//domains/nickbarfuss.com/html/battlegame/" local="3563553260" remote="3565917840" Dst="-1" /><file name="_larger.scss" server="s34242.gridserver.com//domains/nickbarfuss.com/html/battlegame/" local="3563553260" remote="3565917840" Dst="-1" /><file name="_icons.scss" server="s34242.gridserver.com//domains/nickbarfuss.com/html/battlegame/" local="3563553260" remote="3565917840" Dst="-1" /><file name="_list.scss" server="s34242.gridserver.com//domains/nickbarfuss.com/html/battlegame/" local="3563553260" remote="3565917840" Dst="-1" /><file name="_mixins.scss" server="s34242.gridserver.com//domains/nickbarfuss.com/html/battlegame/" local="3563553260" remote="3565917840" Dst="-1" /><file name="_path.scss" server="s34242.gridserver.com//domains/nickbarfuss.com/html/battlegame/" local="3563553260" remote="3565917840" Dst="-1" /><file name="_rotated-flipped.scss" server="s34242.gridserver.com//domains/nickbarfuss.com/html/battlegame/" local="3563553260" remote="3565917840" Dst="-1" /><file name="_screen-reader.scss" server="s34242.gridserver.com//domains/nickbarfuss.com/html/battlegame/" local="3563553260" remote="3565917840" Dst="-1" /><file name="_stacked.scss" server="s34242.gridserver.com//domains/nickbarfuss.com/html/battlegame/" local="3563553260" remote="3565917840" Dst="-1" /><file name="_variables.scss" server="s34242.gridserver.com//domains/nickbarfuss.com/html/battlegame/" local="3564496068" remote="3565917840" Dst="-1" /></dwsync>